{
  "HVIGOR_OHOS_PLUGIN": {
    "MODULES": [
      {
        "MODULE_NAME": "923fe53966c6cd9343e11af776cd4b05be315ea4b200b02e4d5dfb0f929b73bf",
        "API_TYPE": "stageMode",
        "INCREMENTAL_TASKS": {
          "COMPILE_ARKTS": true
        }
      },
      {
        "MODULE_NAME": "791613f2f64ec876ee123bd04961a4554c2b5b7631b64f4ee727ad703d05e17b",
        "API_TYPE": "stageMode",
        "INCREMENTAL_TASKS": {
          "BUILD_NATIVE_WITH_CMAKE": true
        }
      }
    ],
    "NATIVE_COMPILER": "BiSheng",
    "BUILD_MODE": "debug",
    "USE_NORMALIZED_OHMURL": true
  },
  "HVIGOR": {
    "IS_INCREMENTAL": true,
    "IS_DAEMON": true,
    "IS_PARALLEL": true,
    "IS_HVIGORFILE_TYPE_CHECK": false,
    "TASK_TIME": {
      "923fe53966c6cd9343e11af776cd4b05be315ea4b200b02e4d5dfb0f929b73bf": {
        "CreateModuleInfo": 169042,
        "PreCheckSyscap": 169959,
        "ProcessIntegratedHsp": 208625,
        "SyscapTransform": 1334333,
        "ConfigureCmake": 223250,
        "BuildNativeWithCmake": 77875,
        "ProcessStartupConfig": 934083,
        "BuildJS": 1082667,
        "BuildNativeWithNinja": 548292,
        "ProcessLibs": 25818000,
        "DoNativeStrip": 157879916,
        "CacheNativeLibs": 103257458,
        "CompileArkTS": 1951311042,
        "ProcessCompiledResources": 185000,
        "PackageHap": 34957500,
        "PackingCheck": 4153417,
        "SignHap": 291209,
        "CollectDebugSymbol": 171792,
        "assembleHap": 58041
      },
      "791613f2f64ec876ee123bd04961a4554c2b5b7631b64f4ee727ad703d05e17b": {
        "ConfigureCmake": 16681375,
        "BuildNativeWithCmake": 6369500,
        "BuildNativeWithNinja": 248001375
      }
    },
    "APIS": [
      "getHvigorConfig",
      "getRootNodeDescriptor",
      "getChildNode",
      "getNodeByName",
      "getAllNodes",
      "getRootNode",
      "getNodeName",
      "getNodePath",
      "subNodes",
      "getExtraOption",
      "getExtParam",
      "getExtParams",
      "getProperty",
      "getProperties",
      "getParameter",
      "getProductName",
      "nodesEvaluated",
      "getCommandEntryTask",
      "getStartParams"
    ],
    "CONFIG_PROPERTIES": {},
    "TOTAL_TIME": 2163028833,
    "BUILD_ID": "202604060159126090"
  }
}